populi/__init__.py
populi/build.py
populi/cmds.py
populi/driver.py
populi/exceptions.py
populi_mrobison-0.0.7.dist-info/LICENSE
populi_mrobison-0.0.7.dist-info/METADATA
populi_mrobison-0.0.7.dist-info/WHEEL
populi_mrobison-0.0.7.dist-info/top_level.txt
populi_mrobison-0.0.7.dist-info/RECORD
