Metadata-Version: 2.1
Name: populi-mrobison
Version: 0.0.7
Summary: A module for interacting with the populi api.
Home-page: https://github.com/wts-dev/populi-api-python
Author: Mike Robison
Author-email: mrobison@wts.edu
License: UNKNOWN
Platform: UNKNOWN
Classifier: Programming Language :: Python :: 3
Classifier: License :: OSI Approved :: MIT License
Classifier: Operating System :: OS Independent
Requires-Dist: lxml
Requires-Dist: pycurl
